{
  "id": "pet-collecting",
  "slug": "pet-collecting",
  "name": "Pet Collecting",
  "description": "🐶 Relay Mod: Collect various pets with unique abilities by completing actions in-game.",
  "versions": [
    {
      "id": "seAYFB4z",
      "name": "petcollecting-1.19.2-1.0",
      "version_number": "1.0",
      "game_versions": [
        "1.19.2"
      ],
      "loaders": [
        "forge"
      ],
      "files": [
        {
          "sha512": "a7051d4314cf3411dcdc287f4d1e5e119fef264527e6dc172f168a95b7d0b47e9c0dbc577ce5d94ef40b3ef5bdfd30ba18308c04970f12d87a3248f280875a1a",
          "url": "https://cdn.modrinth.com/data/DcFbFceV/versions/seAYFB4z/petcollecting-1.19.2-1.0.jar",
          "filename": "petcollecting-1.19.2-1.0.jar",
          "primary": true,
          "size": 108941
        }
      ]
    }
  ]
}