{
  "id": "ce4AF7M3",
  "slug": "reload-server-list",
  "name": "Reload Server List",
  "description": "Ctrl+R reloads server selection screen",
  "versions": [
    {
      "id": "12Ygry2X",
      "name": "Reload Server List 1.0",
      "version_number": "1.0",
      "game_versions": [
        "1.17",
        "1.17.1",
        "1.18",
        "1.18.1",
        "1.18.2",
        "1.19",
        "1.19.1",
        "1.19.2",
        "1.19.3",
        "1.19.4",
        "1.20",
        "1.20.1",
        "1.20.2",
        "1.20.3",
        "1.20.4",
        "1.20.5",
        "1.20.6",
        "1.21"
      ],
      "loaders": [
        "fabric"
      ],
      "files": [
        {
          "sha512": "3187697b6bb249413b54bd1c84a8148b65dca99b35d65877bc8484463b8bc4d0bd2e3416490b7b7a34d5856766ebb0ab0be96e61605905abbc00fbf3fdea7dda",
          "url": "https://cdn.modrinth.com/data/ce4AF7M3/versions/12Ygry2X/ctrl-r-1.0.jar",
          "filename": "ctrl-r-1.0.jar",
          "primary": true,
          "size": 9088
        }
      ],
      "dependencies": []
    },
    {
      "id": "zOtqAnZU",
      "name": "Reload Server List 1.1",
      "version_number": "1.1",
      "game_versions": [
        "1.17",
        "1.17.1",
        "1.18",
        "1.18.1",
        "1.18.2",
        "1.19",
        "1.19.1",
        "1.19.2",
        "1.19.3",
        "1.19.4",
        "1.20",
        "1.20.1",
        "1.20.2",
        "1.20.3",
        "1.20.4",
        "1.20.5",
        "1.20.6",
        "1.21"
      ],
      "loaders": [
        "fabric"
      ],
      "files": [
        {
          "sha512": "b5e584584fa230b14aef3a9ed16ff438c3c66d4da0491dc2b33d477bce946d0d91b028464665c7a025a060a2265328217fa3c39537e613518270731611c748d3",
          "url": "https://cdn.modrinth.com/data/ce4AF7M3/versions/zOtqAnZU/ctrl-r-1.1.jar",
          "filename": "ctrl-r-1.1.jar",
          "primary": true,
          "size": 9092
        }
      ],
      "dependencies": []
    }
  ]
}