{
  "id": "1HSPVttr",
  "slug": "scandalous-soundboard",
  "name": "Scandalous Soundboard",
  "description": "A scandalous soundboard compatible with Fabric for Minecraft 1.19.2 client and server side!",
  "versions": [
    {
      "id": "9bgXOlDt",
      "name": "Scandalous Soundboard 1.1",
      "version_number": "1.1",
      "game_versions": [
        "1.19.2",
        "1.19.3"
      ],
      "loaders": [
        "fabric"
      ],
      "files": [
        {
          "sha512": "62a38a2608d816c9e51bb4bec8f17be7464d8a5d60ce3a47380b6a8c315c9dae69509e7906f679d26275862493869218faf07a1d360e096a8e9e735659f6bafa",
          "url": "https://cdn.modrinth.com/data/1HSPVttr/versions/9bgXOlDt/soundboard-1.1.jar",
          "filename": "soundboard-1.1.jar",
          "primary": true,
          "size": 26981779
        }
      ],
      "dependencies": []
    },
    {
      "id": "UXYkAxia",
      "name": "Scandalous Soundboard 1.0-SNAPSHOT",
      "version_number": "1.0-SNAPSHOT",
      "game_versions": [
        "1.19.2"
      ],
      "loaders": [
        "fabric"
      ],
      "files": [
        {
          "sha512": "977e4460b122a79b667a611748e386cb1d565bffa010f12e2bb770333be73fd95529cdbab24ce3666fe2857cfbff1c6546a875773bd4259b6797c546c4aca274",
          "url": "https://cdn.modrinth.com/data/1HSPVttr/versions/UXYkAxia/soundboard-1.0-SNAPSHOT.jar",
          "filename": "soundboard-1.0-SNAPSHOT.jar",
          "primary": true,
          "size": 19906
        }
      ],
      "dependencies": [
        {
          "project_id": "P7dR8mSH",
          "version_id": "hfsU4hXq",
          "file_name": null,
          "dependency_type": "required"
        }
      ]
    }
  ]
}