{
  "id": "subtitle_warning_system",
  "slug": "subtitle_warning_system",
  "name": "Subtitle Warning System",
  "description": "Sets all subtitles to blank except creeper hisses, wardens spawning, etc",
  "versions": [
    {
      "id": "1CXd6n7O",
      "name": "Subtitle Warning System",
      "version_number": "1",
      "game_versions": [
        "1.16.5",
        "1.19.2",
        "1.19.4",
        "1.20.1",
        "1.20.4"
      ],
      "loaders": [
        "minecraft"
      ],
      "files": [
        {
          "sha512": "1e96fbe79f77508b5dc600461376c068be410f56903b6f1544e6709738bceedc0a313ef5dfba97e0382ff960bbeedb784013fd65ca405cb15195bfd6d2d237b1",
          "url": "https://cdn.modrinth.com/data/7omoRfpN/versions/1CXd6n7O/subtitle_warning_system.zip",
          "filename": "subtitle_warning_system.zip",
          "primary": true,
          "size": 15598
        }
      ]
    }
  ]
}